[
    {
        "name": "",
        "age": 0,
        "sex": "",
        "chronic_risk": "",
        "heart_condition": "",
        "chest_pains": "",
        "dizzy": "",
        "asthma": "",
        "diabetes": "",
        "other_conditions": "",
        "health_risk": "",
        "weight": 0,
        "height": 0,
        "bmi": 0.0,
        "bmi_rating": "",
        "hip": 0,
        "waist": 0,
        "whr": 0.0,
        "whr_rating": "",
        "heart_rate": 0,
        "hr_rating": ""
    },
    {
        "name": "Chris Apps",
        "age": 40,
        "sex": "male",
        "chronic_risk": "Your age group has a lower risk of chronic health conditions.",
        "heart_condition": "n",
        "chest_pains": "n",
        "dizzy": "n",
        "asthma": "n",
        "diabetes": "n",
        "other_conditions": "n",
        "health_risk": "Exercise presents a low risk to you.",
        "weight": 110.0,
        "height": 185.0,
        "bmi": 32.14,
        "bmi_rating": "Obese I",
        "hip": 120.0,
        "waist": 100.0,
        "whr": 0.83,
        "whr_rating": "Moderate Health Risk",
        "heart_rate": 69.0,
        "hr_rating": "Normal Heart Rate"
    }
]